quantcast_cli/__init__.py
quantcast_cli/__main__.py
quantcast_cli/cookietop.py
quantcast_cli/filters.py
quantcast_cli/search.py
quantcast_cli/time_log.py
quantcast_cli/utils.py
quantcast_cli-0.2.0.dist-info/METADATA
quantcast_cli-0.2.0.dist-info/WHEEL
quantcast_cli-0.2.0.dist-info/entry_points.txt
quantcast_cli-0.2.0.dist-info/licenses/LICENCE
quantcast_cli-0.2.0.dist-info/RECORD
