Metadata-Version: 2.1
Name: quantcast-cli
Version: 0.2.0
Summary: Find the most active cookies CLI
Author-email: Moe Jafari <itismoej@gmail.com>
License-File: LICENCE
Requires-Python: >=3.9
Requires-Dist: pyarrow>=15.0.0
Requires-Dist: typer[all]>=0.9.0
